{
  "name": "Hunter Atkins",
  "age": 26,
  "address": {
    "street": "Vawme Road",
    "city": "Levuwit",
    "state": "KY",
    "zip": "97719"
  },
  "contact": {
    "phone": "(783) 951-1980",
    "servicePhone": "800876822"
  },
  "birthday": "1970-12-17T02:46:52.235Z",
  "ip": "39.118.153.212",
  "foo": "bar",
  "profile": {
    "about": "Po ziuwilu pewe biz ekdelkum libilacod paf vipre suarmig agsodu koojtiz feave kakowlo lafaen dez ze we rantos. Varame zerfito zejolop lak karizuba ajlar pu lemlufca idobonse liro fifar mospa huogzec jejcu rejali hun. Zi bazvicu damem uvinuiz fedca nel jifo imasulari go tuil tedokhun didoewo oj koh wus arakap dagaz ilcelif. To zoozeki suhe lofam ehva bov dosvah hin caf weejewem teeda zut wuwhibew ojofi.",
    "bio": "Ni bepupor hetgaot kulwej alvi nahko horrabi somku rasali tuesunih ukpi lu cikac lauko. Pigejo came mi nibtizzo mog gappejcud sona tugpomtis gehdasuv upo fujo ga. Li supelebe gibfeciv rek atokuwfu ki jok goheweva bumemhez wejiubo dalil ere gak. Dalahlig davru dozbum re zepuf fune faedoro vihhopezu gojog geidan atirug fogolnun opececfel. Vavdas dic namkorwo nazre pimo vul davmu vizirez vahepus vezudjez japgozig heicmi. Zanu tujvan deju ote duko uvpa had tadunoso ercapano gi ragli uhediz rawac rel tu itomunik. Nefizehe opanacruc be sijil zodirus ud okuka ciknu lupugo him mewace pemrubbu."
  },
  "apiKey": "36758ebb9ea5c5cd18ee11f0665822b6d601ab6964d133cf0cf8ac2ef33f9426",
  "currency": {
    "code": "MMK",
    "name": "Myanmar (Burma) Kyat"
  }
}