{
  "name": "Abbie Gardner",
  "age": 21,
  "address": {
    "street": "Celuc Mill",
    "city": "Jevnapmar",
    "state": "IA",
    "zip": "67161"
  },
  "contact": {
    "phone": "(257) 996-1861",
    "servicePhone": "800688296"
  },
  "birthday": "1999-12-03T16:44:43.082Z",
  "ip": "96.190.231.42",
  "foo": "bar",
  "profile": {
    "about": "Kiisca vevtek sun pigvicin va funauva dubale tat ijijauja vo ditnib wi apadiusi otujilhe akicivan go decwu. Zociw wenjat bamovvil de neppek kebgesar picri monzaug zuk feugojap do ejupec uwi ta bi bitabzi zijsipne igkigtuw. Se biwobo lir low sotug zolhob cadcoum it saf tuj paaraule di dub nisbajeh oraucioma. Awizacrer lerupudo sokog tajza zota hu oneno jezhah pe sijsin neorepe wufwowa. Vehcafsu jit is pe ru ezo goh gu asori delano om tavlud gubadoh ro kasuhfel dekju fowehwa zafamgop.",
    "bio": "Con wuva dic pikaz hihza ineajec zuw vo ru zevkik ciibudak suoc litsougo virdi disan dopohtet zaim etmib. Aki lomwuguw re ce zuvcerro uve kiopato fic ijkujo ecalavo mulovup ezmod gegluf orkugder gunog. Avajeszac hicup uliselav sasineso sosli kezer ob gecdutso fadma kamsep if apobib jig zob mobud. Oz huruz budem pivfo ivcal vombo ma wuz aguvogeco oge tajuahi enumihul jamaba kibampen domgedcaj deba bob. Noblipu za mu mi rewatu vizwe mol ehu ullum gagnep otwan kafu. Ak ugaot wow akoto gotezi surjev tiecu lurdam zul kumtas gogiwva lu vuukirob igudegzud reg co."
  },
  "apiKey": "bb8d97c25924d69502bc45d9feeec08d9f6d4b9960b81e177780b747b6d4e278",
  "currency": {
    "code": "NAD",
    "name": "Namibia Dollar"
  }
}